{"3001": {"Name": "Maggi", "MRP": 10, "Quantity": 94, "Weight": "50g", "MFD Date": "20/2/2021", "Expiry Date": "20/10/2021"}, "3002": {"Name": "Soup", "MRP": 20, "Quantity": 96, "Weight": "10g", "MFD Date": "2/3/2021", "Expiry Date": "20/11/2021"}, "3003": {"Name": "Barbon", "MRP": 30, "Quantity": 100, "Weight": "50g", "MFD Date": "25/2/2021", "Expiry Date": "10/12/2022"}, "3004": {"Name": "Parle-G", "MRP": 20, "Quantity": 200, "Weight": "50g", "MFD Date": "11/2/2021", "Expiry Date": "30/10/2022"}, "3005": {"Name": "Perk", "MRP": 5, "Quantity": 200, "Weight": "10g", "MFD Date": "2/8/2021", "Expiry Date": "2/10/2021"}, "3006": {"Name": "Dairy Milk", "MRP": 10, "Quantity": 150, "Weight": "10g", "MFD Date": "20/5/2021", "Expiry Date": "20/9/2021"}, "3007": {"Name": "Marie Gold", "MRP": 20, "Quantity": 200, "Weight": "50g", "MFD Date": "21/5/2021", "Expiry Date": "10/10/2021"}, "3008": {"Name": "Coconut Oil", "MRP": 50, "Quantity": 100, "Weight": "50g", "MFD Date": "20/2/2021", "Expiry Date": "10/10/2021"}, "3009": {"Name": "Maida", "MRP": 100, "Quantity": 50, "Weight": "1kg", "MFD Date": "1/8/2021", "Expiry Date": "2/12/2021"}, "3010": {"Name": "Dal", "MRP": 200, "Quantity": 50, "Weight": "1kg", "MFD Date": "9/7/2021", "Expiry Date": "20/11/2021"}, "3011": {"Name": "Wheat", "MRP": 200, "Quantity": 80, "Weight": "1kg", "MFD Date": "2/3/2021", "Expiry Date": "10/9/2022"}, "3012": {"Name": "Bajara", "MRP": 250, "Quantity": 80, "Weight": "1kg", "MFD Date": "26/2/2021", "Expiry Date": "2/11/2022"}, "3013": {"Name": "Rava", "MRP": 120, "Quantity": 150, "Weight": "1kg", "MFD Date": "28/6/2021", "Expiry Date": "7/10/2021"}, "3014": {"Name": "Cashew", "MRP": 800, "Quantity": 150, "Weight": "1kg", "MFD Date": "27/2/2021", "Expiry Date": "5/10/2021"}, "3015": {"Name": "Peanut", "MRP": 200, "Quantity": 150, "Weight": "1kg", "MFD Date": "17/2/2021", "Expiry Date": "12/11/2021"}, "3016": {"Name": "Almond", "MRP": 800, "Quantity": 150, "Weight": "1kg", "MFD Date": "26/2/2021", "Expiry Date": "19/10/2021"}, "3017": {"Name": "Butter", "MRP": 100, "Quantity": 150, "Weight": "1kg", "MFD Date": "23/3/2021", "Expiry Date": "20/12/2021"}, "3018": {"Name": "Ghee", "MRP": 1000, "Quantity": 50, "Weight": "1kg", "MFD Date": "22/4/2021", "Expiry Date": "2/8/2021"}, "3019": {"Name": "Shampoo", "MRP": 50, "Quantity": 300, "Weight": "1kg", "MFD Date": "20/2/2021", "Expiry Date": "20/9/2021"}, "3020": {"Name": "Talkum", "MRP": 60, "Quantity": 300, "Weight": "1kg", "MFD Date": "20/5/2021", "Expiry Date": "7/12/2023"}, "3021": {"Name": "5 Star", "MRP": 10, "Quantity": 100, "Weight": "50g", "MFD Date": "20/2/2021", "Expiry Date": "20/10/2021"}, "3022": {"Name": "Pasta", "MRP": 20, "Quantity": 10, "Weight": "10g", "MFD Date": "2/6/2021", "Expiry Date": "20/11/2021"}, "3023": {"Name": "Hide N Sick", "MRP": 30, "Quantity": 100, "Weight": "50g", "MFD Date": "25/2/2021", "Expiry Date": "17/12/2022"}, "3024": {"Name": "Chips", "MRP": 20, "Quantity": 200, "Weight": "500g", "MFD Date": "11/5/2021", "Expiry Date": "30/10/2022"}, "3025": {"Name": "kurkure", "MRP": 5, "Quantity": 20, "Weight": "100g", "MFD Date": "2/8/2021", "Expiry Date": "2/10/2021"}, "3026": {"Name": "Munch", "MRP": 10, "Quantity": 150, "Weight": "10g", "MFD Date": "20/5/2021", "Expiry Date": "16/9/2021"}, "3027": {"Name": "Coconut Biscuits", "MRP": 20, "Quantity": 200, "Weight": "50g", "MFD Date": "21/5/2021", "Expiry Date": "10/10/2021"}, "3028": {"Name": "Bhel", "MRP": 50, "Quantity": 10, "Weight": "500g", "MFD Date": "2/2/2021", "Expiry Date": "15/10/2021"}, "3029": {"Name": "Jaggery", "MRP": 100, "Quantity": 50, "Weight": "1kg", "MFD Date": "1/8/2021", "Expiry Date": "2/12/2021"}, "3030": {"Name": "Masur", "MRP": 200, "Quantity": 50, "Weight": "1kg", "MFD Date": "9/7/2021", "Expiry Date": "20/11/2021"}, "3031": {"Name": "Lotion", "MRP": 200, "Quantity": 80, "Weight": "1kg", "MFD Date": "22/3/2021", "Expiry Date": "11/9/2021"}, "3032": {"Name": "Bread", "MRP": 25, "Quantity": 80, "Weight": "1kg", "MFD Date": "26/2/2021", "Expiry Date": "2/11/2022"}, "3033": {"Name": "Conditioner", "MRP": 120, "Quantity": 15, "Weight": "200g", "MFD Date": "28/6/2021", "Expiry Date": "7/10/2021"}, "3034": {"Name": "Rice", "MRP": 200, "Quantity": 150, "Weight": "1kg", "MFD Date": "27/2/2021", "Expiry Date": "5/10/2021"}, "3035": {"Name": "Sugar", "MRP": 200, "Quantity": 150, "Weight": "1kg", "MFD Date": "17/2/2021", "Expiry Date": "12/11/2021"}, "3036": {"Name": "Salt", "MRP": 80, "Quantity": 150, "Weight": "1kg", "MFD Date": "26/2/2021", "Expiry Date": "19/10/2021"}, "3037": {"Name": "Red Chutney", "MRP": 25, "Quantity": 150, "Weight": "1kg", "MFD Date": "23/3/2021", "Expiry Date": "20/12/2021"}, "3038": {"Name": "Tomato Ketchup", "MRP": 10, "Quantity": 50, "Weight": "1kg", "MFD Date": "22/5/2021", "Expiry Date": "2/10/2021"}, "3039": {"Name": "Pickel", "MRP": 50, "Quantity": 30, "Weight": "1kg", "MFD Date": "20/2/2021", "Expiry Date": "20/9/2021"}, "3040": {"Name": "Soya Souce", "MRP": 60, "Quantity": 20, "Weight": "1kg", "MFD Date": "20/7/2021", "Expiry Date": "7/8/2023"}}